Workbook

Sheet 68-jan
A1: บริษัท ไอน์ชไตน์ อินดัสเตรียล เทคนิค คอร์ปอเรชั่น จำกัด
A2: (สำนักงานใหญ่) เลขที่ : 1/120 ซอยรามคำแหง 184 แขวงมีนบุรี เขตมีนบุรี กรุงเทพมหานคร 10510
A3: Tel : 0-2052-9544 Fax : 0-2052-9544 E-mail : sales@eitlaser.com
A5: ใบจ่ายเงินเดือน / Pay Slip
D7: รหัสพนักงาน / Code Staff / ID | F7: =+'ใบสรุป-68'!C6 -> 630617 | G7: =+'ใบสรุป-68'!D6 -> 1102002947799 | I7: วันที่/ Date
D8: แผนก / Department | F8: =+'ใบสรุป-68'!C7 -> Technician | I8: 01/02/2568
D9: ฝ่าย / Division | F9: =+'ใบสรุป-68'!C8 -> Factory | I9: เดือน/ For Month
D10: ตำแหน่ง / Position | F10: =+'ใบสรุป-68'!C9 -> Technician | I10: มกราคม /January
A11: ชื่อ - นามสกุล | B11: =+'ใบสรุป-68'!C4 -> Mr.Anuwat Surarit
A12: Name - Surname | B12: =+'ใบสรุป-68'!C5 -> นายอนุวัฒน์ สุราฤทธิ์
A14: รายการรับ | B14: เงินเดือน | C14: ค่าล่วงเวลา | D14: ค่าเบี้ยขยัน | E14: ค่าคอมมิชชั่น | F14: อื่น ๆ | G14: อื่น ๆ | I14: รวมเงินได้ทั้งสิ้น
A15: Income | B15: Salary | C15: Over time | E15: Commission | F15: Other | G15: Other | I15: Total Income
B16: =20959+750 -> 21709 | F16: 0 | G16: 0 | I16: =SUM(B16+C16+D16+E16+F16+G16) -> 21709
A18: รายการหัก | B18: ภาษี | C18: ประกันสังคม | D18: รายการ-อื่น ๆ | E18: อื่น ๆ | I18: รวมเงินหักทั้งสิ้น
A19: Reduction | B19: Income WHT | C19: Social Security Tax | D19: Other | E19: Other | I19: Total Reduction
B20: 0 | C20: 750 | D20: 0 | E20: 0 | I20: =+B20+C20+D20+E20 -> 750
A22: ยอดสะสม | B22: รายได้-สะสม | C22: ประกันสังคม-สะสม | D22: ภาษี-สะสม | E22: อื่น ๆ-สะสม | I22: รายได้สุทธิ
A23: Total Collection | B23: Collection Income | C23: Collection Social WHT | D23: Collection Income WHT | E23: Collection-Other | I23: Net Income
B24: =I16 -> 21709 | C24: =C20 -> 750 | D24: =B20 -> 0 | E24: =F16+G16+D20+E20 -> 0 | I24: =+I16-I20 -> 20959

Sheet 68-Feb
A1: บริษัท ไอน์ชไตน์ อินดัสเตรียล เทคนิค คอร์ปอเรชั่น จำกัด
A2: (สำนักงานใหญ่) เลขที่ : 1/120 ซอยรามคำแหง 184 แขวงมีนบุรี เขตมีนบุรี กรุงเทพมหานคร 10510
A3: Tel : 0-2052-9544 Fax : 0-2052-9544 E-mail : sales@eitlaser.com
A5: ใบจ่ายเงินเดือน / Pay Slip
D7: รหัสพนักงาน / Code Staff / ID | F7: =+'ใบสรุป-68'!C6 -> 630617 | G7: =+'ใบสรุป-68'!D6 -> 1102002947799 | I7: วันที่/ Date
D8: แผนก / Department | F8: =+'ใบสรุป-68'!C7 -> Technician | I8: 01/03/2568
D9: ฝ่าย / Division | F9: =+'ใบสรุป-68'!C8 -> Factory | I9: เดือน/ For Month
D10: ตำแหน่ง / Position | F10: =+'ใบสรุป-68'!C9 -> Technician | I10: กุมภาพันธ์ /February
A11: ชื่อ - นามสกุล | B11: =+'ใบสรุป-68'!C4 -> Mr.Anuwat Surarit
A12: Name - Surname | B12: =+'ใบสรุป-68'!C5 -> นายอนุวัฒน์ สุราฤทธิ์
A14: รายการรับ | B14: เงินเดือน | C14: ค่าล่วงเวลา | D14: ค่าเบี้ยขยัน | E14: ค่าคอมมิชชั่น | F14: อื่น ๆ | G14: อื่น ๆ | I14: รวมเงินได้ทั้งสิ้น
A15: Income | B15: Salary | C15: Over time | E15: Commission | F15: Other | G15: Other | I15: Total Income
B16: =20830+750 -> 21580 | F16: 0 | G16: 0 | I16: =SUM(B16+C16+D16+E16+F16+G16) -> 21580
A18: รายการหัก | B18: ภาษี | C18: ประกันสังคม | D18: รายการ-อื่น ๆ | E18: อื่น ๆ | I18: รวมเงินหักทั้งสิ้น
A19: Reduction | B19: Income WHT | C19: Social Security Tax | D19: Other | E19: Other | I19: Total Reduction
B20: 0 | C20: 750 | D20: 0 | E20: 0 | I20: =+B20+C20+D20+E20 -> 750
A22: ยอดสะสม | B22: รายได้-สะสม | C22: ประกันสังคม-สะสม | D22: ภาษี-สะสม | E22: อื่น ๆ-สะสม | I22: รายได้สุทธิ
A23: Total Collection | B23: Collection Income | C23: Collection Social WHT | D23: Collection Income WHT | E23: Collection-Other | I23: Net Income
B24: =I16+'68-jan'!B24 -> 43289 | C24: =C20+'68-jan'!C24 -> 1500 | D24: =B20+'68-jan'!D24 -> 0 | I24: =I16-I20 -> 20830

Sheet 68-Mar
A1: บริษัท ไอน์ชไตน์ อินดัสเตรียล เทคนิค คอร์ปอเรชั่น จำกัด
A2: (สำนักงานใหญ่) เลขที่ : 1/120 ซอยรามคำแหง 184 แขวงมีนบุรี เขตมีนบุรี กรุงเทพมหานคร 10510
A3: Tel : 0-2052-9544 Fax : 0-2052-9544 E-mail : sales@eitlaser.com
A5: ใบจ่ายเงินเดือน / Pay Slip
D7: รหัสพนักงาน / Code Staff / ID | F7: =+'ใบสรุป-68'!C6 -> 630617 | G7: =+'ใบสรุป-68'!D6 -> 1102002947799 | I7: วันที่/ Date
D8: แผนก / Department | F8: =+'ใบสรุป-68'!C7 -> Technician | I8: 01/04/2568
D9: ฝ่าย / Division | F9: =+'ใบสรุป-68'!C8 -> Factory | I9: เดือน/ For Month
D10: ตำแหน่ง / Position | F10: =+'ใบสรุป-68'!C9 -> Technician | I10: มีนาคม /March
A11: ชื่อ - นามสกุล | B11: =+'ใบสรุป-68'!C4 -> Mr.Anuwat Surarit
A12: Name - Surname | B12: =+'ใบสรุป-68'!C5 -> นายอนุวัฒน์ สุราฤทธิ์
A14: รายการรับ | B14: เงินเดือน | C14: ค่าล่วงเวลา | D14: ค่าเบี้ยขยัน | E14: ค่าคอมมิชชั่น | F14: อื่น ๆ | G14: อื่น ๆ | I14: รวมเงินได้ทั้งสิ้น
A15: Income | B15: Salary | C15: Over time | E15: Commission | F15: Other | G15: Other | I15: Total Income
B16: =20678+750 -> 21428 | F16: 0 | G16: 0 | I16: =SUM(B16+C16+D16+E16+F16+G16) -> 21428
A18: รายการหัก | B18: ภาษี | C18: ประกันสังคม | D18: รายการ-อื่น ๆ | E18: อื่น ๆ | I18: รวมเงินหักทั้งสิ้น
A19: Reduction | B19: Income WHT | C19: Social Security Tax | D19: Other | E19: Other | I19: Total Reduction
B20: 0 | C20: 750 | D20: 0 | E20: 0 | I20: =+B20+C20+D20+E20 -> 750
A22: ยอดสะสม | B22: รายได้-สะสม | C22: ประกันสังคม-สะสม | D22: ภาษี-สะสม | E22: อื่น ๆ-สะสม | I22: รายได้สุทธิ
A23: Total Collection | B23: Collection Income | C23: Collection Social WHT | D23: Collection Income WHT | E23: Collection-Other | I23: Net Income
B24: =I16+'68-Feb'!B24 -> 64717 | C24: =C20+'68-Feb'!C24 -> 2250 | D24: =B20+'68-Feb'!D24 -> 0 | I24: =+I16-I20 -> 20678

Sheet 68-Apr
A1: บริษัท ไอน์ชไตน์ อินดัสเตรียล เทคนิค คอร์ปอเรชั่น จำกัด
A2: (สำนักงานใหญ่) เลขที่ : 1/120 ซอยรามคำแหง 184 แขวงมีนบุรี เขตมีนบุรี กรุงเทพมหานคร 10510
A3: Tel : 0-2052-9544 Fax : 0-2052-9544 E-mail : sales@eitlaser.com
A5: ใบจ่ายเงินเดือน / Pay Slip
D7: รหัสพนักงาน / Code Staff / ID | F7: =+'ใบสรุป-68'!C6 -> 630617 | G7: =+'ใบสรุป-68'!D6 -> 1102002947799 | I7: วันที่/ Date
D8: แผนก / Department | F8: =+'ใบสรุป-68'!C7 -> Technician | I8: 01/05/2568
D9: ฝ่าย / Division | F9: =+'ใบสรุป-68'!C8 -> Factory | I9: เดือน/ For Month
D10: ตำแหน่ง / Position | F10: =+'ใบสรุป-68'!C9 -> Technician | I10: เมษายน /April
A11: ชื่อ - นามสกุล | B11: =+'ใบสรุป-68'!C4 -> Mr.Anuwat Surarit
A12: Name - Surname | B12: =+'ใบสรุป-68'!C5 -> นายอนุวัฒน์ สุราฤทธิ์
A14: รายการรับ | B14: เงินเดือน | C14: ค่าล่วงเวลา | D14: ค่าเบี้ยขยัน | E14: ค่าคอมมิชชั่น | F14: อื่น ๆ | G14: อื่น ๆ | I14: รวมเงินได้ทั้งสิ้น
A15: Income | B15: Salary | C15: Over time | E15: Commission | F15: Other | G15: Other | I15: Total Income
B16: =22411+750 -> 23161 | F16: 0 | G16: 0 | I16: =SUM(B16+C16+D16+E16+F16+G16) -> 23161
A18: รายการหัก | B18: ภาษี | C18: ประกันสังคม | D18: รายการ-อื่น ๆ | E18: อื่น ๆ | I18: รวมเงินหักทั้งสิ้น
A19: Reduction | B19: Income WHT | C19: Social Security Tax | D19: Other | E19: Other | I19: Total Reduction
B20: 0 | C20: 750 | D20: 0 | E20: 0 | I20: =+B20+C20+D20+E20 -> 750
A22: ยอดสะสม | B22: รายได้-สะสม | C22: ประกันสังคม-สะสม | D22: ภาษี-สะสม | E22: อื่น ๆ-สะสม | I22: รายได้สุทธิ
A23: Total Collection | B23: Collection Income | C23: Collection Social WHT | D23: Collection Income WHT | E23: Collection-Other | I23: Net Income
B24: =I16+'68-Mar'!B24 -> 87878 | C24: =C20+'68-Mar'!C24 -> 3000 | D24: =B20+'68-Mar'!D24 -> 0 | I24: =+I16-I20 -> 22411

Sheet 68-May
A1: บริษัท ไอน์ชไตน์ อินดัสเตรียล เทคนิค คอร์ปอเรชั่น จำกัด
A2: (สำนักงานใหญ่) เลขที่ : 1/120 ซอยรามคำแหง 184 แขวงมีนบุรี เขตมีนบุรี กรุงเทพมหานคร 10510
A3: Tel : 0-2052-9544 Fax : 0-2052-9544 E-mail : sales@eitlaser.com
A5: ใบจ่ายเงินเดือน / Pay Slip
D7: รหัสพนักงาน / Code Staff / ID | F7: =+'ใบสรุป-68'!C6 -> 630617 | G7: =+'ใบสรุป-68'!D6 -> 1102002947799 | I7: วันที่/ Date
D8: แผนก / Department | F8: =+'ใบสรุป-68'!C7 -> Technician | I8: 01/06/2568
D9: ฝ่าย / Division | F9: =+'ใบสรุป-68'!C8 -> Factory | I9: เดือน/ For Month
D10: ตำแหน่ง / Position | F10: =+'ใบสรุป-68'!C9 -> Technician | I10: พฤษภาคม /May
A11: ชื่อ - นามสกุล | B11: =+'ใบสรุป-68'!C4 -> Mr.Anuwat Surarit
A12: Name - Surname | B12: =+'ใบสรุป-68'!C5 -> นายอนุวัฒน์ สุราฤทธิ์
A14: รายการรับ | B14: เงินเดือน | C14: ค่าล่วงเวลา | D14: ค่าเบี้ยขยัน | E14: ค่าคอมมิชชั่น | F14: อื่น ๆ | G14: อื่น ๆ | I14: รวมเงินได้ทั้งสิ้น
A15: Income | B15: Salary | C15: Over time | E15: Commission | F15: Other | G15: Other | I15: Total Income
B16: =21666+750 -> 22416 | F16: 0 | G16: 0 | I16: =SUM(B16+C16+D16+E16+F16+G16) -> 22416
A18: รายการหัก | B18: ภาษี | C18: ประกันสังคม | D18: รายการ-อื่น ๆ | E18: อื่น ๆ | I18: รวมเงินหักทั้งสิ้น
A19: Reduction | B19: Income WHT | C19: Social Security Tax | D19: Other | E19: Other | I19: Total Reduction
B20: 0 | C20: 750 | D20: 0 | E20: 0 | I20: =+B20+C20+D20+E20 -> 750
A22: ยอดสะสม | B22: รายได้-สะสม | C22: ประกันสังคม-สะสม | D22: ภาษี-สะสม | E22: อื่น ๆ-สะสม | I22: รายได้สุทธิ
A23: Total Collection | B23: Collection Income | C23: Collection Social WHT | D23: Collection Income WHT | E23: Collection-Other | I23: Net Income
B24: =I16+'68-Apr'!B24 -> 110294 | C24: =C20+'68-Apr'!C24 -> 3750 | D24: =B20+'68-Apr'!D24 -> 0 | I24: =+I16-I20 -> 21666

Sheet 68-Jun
A1: บริษัท ไอน์ชไตน์ อินดัสเตรียล เทคนิค คอร์ปอเรชั่น จำกัด
A2: (สำนักงานใหญ่) เลขที่ : 1/120 ซอยรามคำแหง 184 แขวงมีนบุรี เขตมีนบุรี กรุงเทพมหานคร 10510
A3: Tel : 0-2052-9544 Fax : 0-2052-9544 E-mail : sales@eitlaser.com
A5: ใบจ่ายเงินเดือน / Pay Slip
D7: รหัสพนักงาน / Code Staff / ID | F7: =+'ใบสรุป-68'!C6 -> 630617 | G7: =+'ใบสรุป-68'!D6 -> 1102002947799 | I7: วันที่/ Date
D8: แผนก / Department | F8: =+'ใบสรุป-68'!C7 -> Technician | I8: 01/07/2568
D9: ฝ่าย / Division | F9: =+'ใบสรุป-68'!C8 -> Factory | I9: เดือน/ For Month
D10: ตำแหน่ง / Position | F10: =+'ใบสรุป-68'!C9 -> Technician | I10: มิถุนายน /June
A11: ชื่อ - นามสกุล | B11: =+'ใบสรุป-68'!C4 -> Mr.Anuwat Surarit
A12: Name - Surname | B12: =+'ใบสรุป-68'!C5 -> นายอนุวัฒน์ สุราฤทธิ์
A14: รายการรับ | B14: เงินเดือน | C14: ค่าล่วงเวลา | D14: ค่าเบี้ยขยัน | E14: ค่าคอมมิชชั่น | F14: อื่น ๆ | G14: อื่น ๆ | I14: รวมเงินได้ทั้งสิ้น
A15: Income | B15: Salary | C15: Over time | E15: Commission | F15: Other | G15: Other | I15: Total Income
B16: =22266+750 -> 23016 | F16: 0 | G16: 0 | I16: =SUM(B16+C16+D16+E16+F16+G16) -> 23016
A18: รายการหัก | B18: ภาษี | C18: ประกันสังคม | D18: รายการ-อื่น ๆ | E18: อื่น ๆ | I18: รวมเงินหักทั้งสิ้น
A19: Reduction | B19: Income WHT | C19: Social Security Tax | D19: Other | E19: Other | I19: Total Reduction
B20: 0 | C20: 750 | D20: 0 | E20: 0 | I20: =+B20+C20+D20+E20 -> 750
A22: ยอดสะสม | B22: รายได้-สะสม | C22: ประกันสังคม-สะสม | D22: ภาษี-สะสม | E22: อื่น ๆ-สะสม | I22: รายได้สุทธิ
A23: Total Collection | B23: Collection Income | C23: Collection Social WHT | D23: Collection Income WHT | E23: Collection-Other | I23: Net Income
B24: =I16+'68-May'!B24 -> 133310 | C24: =C20+'68-May'!C24 -> 4500 | D24: =B20+'68-May'!D24 -> 0 | I24: =+I16-I20 -> 22266

Sheet 68-Jul
A1: บริษัท ไอน์ชไตน์ อินดัสเตรียล เทคนิค คอร์ปอเรชั่น จำกัด
A2: (สำนักงานใหญ่) เลขที่ : 1/120 ซอยรามคำแหง 184 แขวงมีนบุรี เขตมีนบุรี กรุงเทพมหานคร 10510
A3: Tel : 0-2052-9544 Fax : 0-2052-9544 E-mail : sales@eitlaser.com
A5: ใบจ่ายเงินเดือน / Pay Slip
D7: รหัสพนักงาน / Code Staff / ID | F7: =+'ใบสรุป-68'!C6 -> 630617 | G7: =+'ใบสรุป-68'!D6 -> 1102002947799 | I7: วันที่/ Date
D8: แผนก / Department | F8: =+'ใบสรุป-68'!C7 -> Technician | I8: 01/08/2568
D9: ฝ่าย / Division | F9: =+'ใบสรุป-68'!C8 -> Factory | I9: เดือน/ For Month
D10: ตำแหน่ง / Position | F10: =+'ใบสรุป-68'!C9 -> Technician | I10: กรกฎาคม /July
A11: ชื่อ - นามสกุล | B11: =+'ใบสรุป-68'!C4 -> Mr.Anuwat Surarit
A12: Name - Surname | B12: =+'ใบสรุป-68'!C5 -> นายอนุวัฒน์ สุราฤทธิ์
A14: รายการรับ | B14: เงินเดือน | C14: ค่าล่วงเวลา | D14: ค่าเบี้ยขยัน | E14: ค่าคอมมิชชั่น | F14: อื่น ๆ | G14: อื่น ๆ | I14: รวมเงินได้ทั้งสิ้น
A15: Income | B15: Salary | C15: Over time | E15: Commission | F15: Other | G15: Other | I15: Total Income
B16: =22000+750 -> 22750 | F16: 0 | G16: 0 | I16: =SUM(B16+C16+D16+E16+F16+G16) -> 22750
A18: รายการหัก | B18: ภาษี | C18: ประกันสังคม | D18: รายการ-อื่น ๆ | E18: อื่น ๆ | I18: รวมเงินหักทั้งสิ้น
A19: Reduction | B19: Income WHT | C19: Social Security Tax | D19: Other | E19: Other | I19: Total Reduction
B20: 0 | C20: 750 | D20: 0 | E20: 0 | I20: =+B20+C20+D20+E20 -> 750
A22: ยอดสะสม | B22: รายได้-สะสม | C22: ประกันสังคม-สะสม | D22: ภาษี-สะสม | E22: อื่น ๆ-สะสม | I22: รายได้สุทธิ
A23: Total Collection | B23: Collection Income | C23: Collection Social WHT | D23: Collection Income WHT | E23: Collection-Other | I23: Net Income
B24: =I16+'68-Jun'!B24 -> 156060 | C24: =C20+'68-Jun'!C24 -> 5250 | D24: =B20+'68-Jun'!D24 -> 0 | I24: =+I16-I20 -> 22000

Sheet 68-Aug
A1: บริษัท ไอน์ชไตน์ อินดัสเตรียล เทคนิค คอร์ปอเรชั่น จำกัด
A2: (สำนักงานใหญ่) เลขที่ : 1/120 ซอยรามคำแหง 184 แขวงมีนบุรี เขตมีนบุรี กรุงเทพมหานคร 10510
A3: Tel : 0-2052-9544 Fax : 0-2052-9544 E-mail : sales@eitlaser.com
A5: ใบจ่ายเงินเดือน / Pay Slip
D7: รหัสพนักงาน / Code Staff / ID | F7: =+'ใบสรุป-68'!C6 -> 630617 | G7: =+'ใบสรุป-68'!D6 -> 1102002947799 | I7: วันที่/ Date
D8: แผนก / Department | F8: =+'ใบสรุป-68'!C7 -> Technician | I8: 01/09/2568
D9: ฝ่าย / Division | F9: =+'ใบสรุป-68'!C8 -> Factory | I9: เดือน/ For Month
D10: ตำแหน่ง / Position | F10: =+'ใบสรุป-68'!C9 -> Technician | I10: สิงหาคม /August
A11: ชื่อ - นามสกุล | B11: =+'ใบสรุป-68'!C4 -> Mr.Anuwat Surarit
A12: Name - Surname | B12: =+'ใบสรุป-68'!C5 -> นายอนุวัฒน์ สุราฤทธิ์
A14: รายการรับ | B14: เงินเดือน | C14: ค่าล่วงเวลา | D14: ค่าเบี้ยขยัน | E14: ค่าคอมมิชชั่น | F14: อื่น ๆ | G14: อื่น ๆ | I14: รวมเงินได้ทั้งสิ้น
A15: Income | B15: Salary | C15: Over time | E15: Commission | F15: Other | G15: Other | I15: Total Income
B16: =20934+750 -> 21684 | F16: 0 | G16: 0 | I16: =SUM(B16+C16+D16+E16+F16+G16) -> 21684
A18: รายการหัก | B18: ภาษี | C18: ประกันสังคม | D18: รายการ-อื่น ๆ | E18: อื่น ๆ | I18: รวมเงินหักทั้งสิ้น
A19: Reduction | B19: Income WHT | C19: Social Security Tax | D19: Other | E19: Other | I19: Total Reduction
B20: 0 | C20: 750 | D20: 0 | E20: 0 | I20: =+B20+C20+D20+E20 -> 750
A22: ยอดสะสม | B22: รายได้-สะสม | C22: ประกันสังคม-สะสม | D22: ภาษี-สะสม | E22: อื่น ๆ-สะสม | I22: รายได้สุทธิ
A23: Total Collection | B23: Collection Income | C23: Collection Social WHT | D23: Collection Income WHT | E23: Collection-Other | I23: Net Income
B24: =I16+'68-Jul'!B24 -> 177744 | C24: =C20+'68-Jul'!C24 -> 6000 | D24: =B20+'68-Jul'!D24 -> 0 | I24: =+I16-I20 -> 20934

Sheet 68-Sep
A1: บริษัท ไอน์ชไตน์ อินดัสเตรียล เทคนิค คอร์ปอเรชั่น จำกัด
A2: (สำนักงานใหญ่) เลขที่ : 1/120 ซอยรามคำแหง 184 แขวงมีนบุรี เขตมีนบุรี กรุงเทพมหานคร 10510
A3: Tel : 0-2052-9544 Fax : 0-2052-9544 E-mail : sales@eitlaser.com
A5: ใบจ่ายเงินเดือน / Pay Slip
D7: รหัสพนักงาน / Code Staff / ID | F7: =+'ใบสรุป-68'!C6 -> 630617 | G7: =+'ใบสรุป-68'!D6 -> 1102002947799 | I7: วันที่/ Date
D8: แผนก / Department | F8: =+'ใบสรุป-68'!C7 -> Technician | I8: 01/10/2568
D9: ฝ่าย / Division | F9: =+'ใบสรุป-68'!C8 -> Factory | I9: เดือน/ For Month
D10: ตำแหน่ง / Position | F10: =+'ใบสรุป-68'!C9 -> Technician | I10: กันยายน /September
A11: ชื่อ - นามสกุล | B11: =+'ใบสรุป-68'!C4 -> Mr.Anuwat Surarit
A12: Name - Surname | B12: =+'ใบสรุป-68'!C5 -> นายอนุวัฒน์ สุราฤทธิ์
A14: รายการรับ | B14: เงินเดือน | C14: ค่าล่วงเวลา | D14: ค่าเบี้ยขยัน | E14: ค่าคอมมิชชั่น | F14: อื่น ๆ | G14: อื่น ๆ | I14: รวมเงินได้ทั้งสิ้น
A15: Income | B15: Salary | C15: Over time | E15: Commission | F15: Other | G15: Other | I15: Total Income
B16: =20985+750 -> 21735 | F16: 0 | G16: 0 | I16: =SUM(B16+C16+D16+E16+F16+G16) -> 21735
A18: รายการหัก | B18: ภาษี | C18: ประกันสังคม | D18: รายการ-อื่น ๆ | E18: อื่น ๆ | I18: รวมเงินหักทั้งสิ้น
A19: Reduction | B19: Income WHT | C19: Social Security Tax | D19: Other | E19: Other | I19: Total Reduction
B20: 0 | C20: 750 | D20: 0 | E20: 0 | I20: =+B20+C20+D20+E20 -> 750
A22: ยอดสะสม | B22: รายได้-สะสม | C22: ประกันสังคม-สะสม | D22: ภาษี-สะสม | E22: อื่น ๆ-สะสม | I22: รายได้สุทธิ
A23: Total Collection | B23: Collection Income | C23: Collection Social WHT | D23: Collection Income WHT | E23: Collection-Other | I23: Net Income
B24: =I16+'68-Aug'!B24 -> 199479 | C24: =C20+'68-Aug'!C24 -> 6750 | D24: =B20+'68-Aug'!D24 -> 0 | I24: =+I16-I20 -> 20985

Sheet 68-Oct
A1: บริษัท ไอน์ชไตน์ อินดัสเตรียล เทคนิค คอร์ปอเรชั่น จำกัด
A2: (สำนักงานใหญ่) เลขที่ : 1/120 ซอยรามคำแหง 184 แขวงมีนบุรี เขตมีนบุรี กรุงเทพมหานคร 10510
A3: Tel : 0-2052-9544 Fax : 0-2052-9544 E-mail : sales@eitlaser.com
A5: ใบจ่ายเงินเดือน / Pay Slip
D7: รหัสพนักงาน / Code Staff / ID | F7: =+'ใบสรุป-68'!C6 -> 630617 | G7: =+'ใบสรุป-68'!D6 -> 1102002947799 | I7: วันที่/ Date
D8: แผนก / Department | F8: =+'ใบสรุป-68'!C7 -> Technician | I8: 01/11/2568
D9: ฝ่าย / Division | F9: =+'ใบสรุป-68'!C8 -> Factory | I9: เดือน/ For Month
D10: ตำแหน่ง / Position | F10: =+'ใบสรุป-68'!C9 -> Technician | I10: ตุลาคม /October
A11: ชื่อ - นามสกุล | B11: =+'ใบสรุป-68'!C4 -> Mr.Anuwat Surarit
A12: Name - Surname | B12: =+'ใบสรุป-68'!C5 -> นายอนุวัฒน์ สุราฤทธิ์
A14: รายการรับ | B14: เงินเดือน | C14: ค่าล่วงเวลา | D14: ค่าเบี้ยขยัน | E14: ค่าคอมมิชชั่น | F14: อื่น ๆ | G14: อื่น ๆ | I14: รวมเงินได้ทั้งสิ้น
A15: Income | B15: Salary | C15: Over time | E15: Commission | F15: Other | G15: Other | I15: Total Income
B16: =23343+750 -> 24093 | F16: 0 | G16: 0 | I16: =SUM(B16+C16+D16+E16+F16+G16) -> 24093
A18: รายการหัก | B18: ภาษี | C18: ประกันสังคม | D18: รายการ-อื่น ๆ | E18: อื่น ๆ | I18: รวมเงินหักทั้งสิ้น
A19: Reduction | B19: Income WHT | C19: Social Security Tax | D19: Other | E19: Other | I19: Total Reduction
B20: 0 | C20: 750 | D20: 0 | E20: 0 | I20: =+B20+C20+D20+E20 -> 750
A22: ยอดสะสม | B22: รายได้-สะสม | C22: ประกันสังคม-สะสม | D22: ภาษี-สะสม | E22: อื่น ๆ-สะสม | I22: รายได้สุทธิ
A23: Total Collection | B23: Collection Income | C23: Collection Social WHT | D23: Collection Income WHT | E23: Collection-Other | I23: Net Income
B24: =I16+'68-Sep'!B24 -> 223572 | C24: =C20+'68-Sep'!C24 -> 7500 | D24: =B20+'68-Sep'!D24 -> 0 | I24: =+I16-I20 -> 23343

Sheet 68-Nov
A1: บริษัท ไอน์ชไตน์ อินดัสเตรียล เทคนิค คอร์ปอเรชั่น จำกัด
A2: (สำนักงานใหญ่) เลขที่ : 1/120 ซอยรามคำแหง 184 แขวงมีนบุรี เขตมีนบุรี กรุงเทพมหานคร 10510
A3: Tel : 0-2052-9544 Fax : 0-2052-9544 E-mail : sales@eitlaser.com
A5: ใบจ่ายเงินเดือน / Pay Slip
D7: รหัสพนักงาน / Code Staff / ID | F7: =+'ใบสรุป-68'!C6 -> 630617 | G7: =+'ใบสรุป-68'!D6 -> 1102002947799 | I7: วันที่/ Date
D8: แผนก / Department | F8: =+'ใบสรุป-68'!C7 -> Technician | I8: 01/12/2568
D9: ฝ่าย / Division | F9: =+'ใบสรุป-68'!C8 -> Factory | I9: เดือน/ For Month
D10: ตำแหน่ง / Position | F10: =+'ใบสรุป-68'!C9 -> Technician | I10: พฤศจิกายน /November
A11: ชื่อ - นามสกุล | B11: =+'ใบสรุป-68'!C4 -> Mr.Anuwat Surarit
A12: Name - Surname | B12: =+'ใบสรุป-68'!C5 -> นายอนุวัฒน์ สุราฤทธิ์
A14: รายการรับ | B14: เงินเดือน | C14: ค่าล่วงเวลา | D14: ค่าเบี้ยขยัน | E14: ค่าคอมมิชชั่น | F14: อื่น ๆ | G14: อื่น ๆ | I14: รวมเงินได้ทั้งสิ้น
A15: Income | B15: Salary | C15: Over time | E15: Commission | F15: Other | G15: Other | I15: Total Income
B16: =22033+750 -> 22783 | F16: 0 | G16: 0 | I16: =SUM(B16+C16+D16+E16+F16+G16) -> 22783
A18: รายการหัก | B18: ภาษี | C18: ประกันสังคม | D18: รายการ-อื่น ๆ | E18: อื่น ๆ | I18: รวมเงินหักทั้งสิ้น
A19: Reduction | B19: Income WHT | C19: Social Security Tax | D19: Other | E19: Other | I19: Total Reduction
B20: 0 | C20: 750 | D20: 0 | E20: 0 | I20: =+B20+C20+D20+E20 -> 750
A22: ยอดสะสม | B22: รายได้-สะสม | C22: ประกันสังคม-สะสม | D22: ภาษี-สะสม | E22: อื่น ๆ-สะสม | I22: รายได้สุทธิ
A23: Total Collection | B23: Collection Income | C23: Collection Social WHT | D23: Collection Income WHT | E23: Collection-Other | I23: Net Income
B24: =I16+'68-Oct'!B24 -> 246355 | C24: =C20+'68-Oct'!C24 -> 8250 | D24: =B20+'68-Oct'!D24 -> 0 | I24: =+I16-I20 -> 22033

Sheet 68-Dec
A1: บริษัท ไอน์ชไตน์ อินดัสเตรียล เทคนิค คอร์ปอเรชั่น จำกัด
A2: (สำนักงานใหญ่) เลขที่ : 1/120 ซอยรามคำแหง 184 แขวงมีนบุรี เขตมีนบุรี กรุงเทพมหานคร 10510
A3: Tel : 0-2052-9544 Fax : 0-2052-9544 E-mail : sales@eitlaser.com
A5: ใบจ่ายเงินเดือน / Pay Slip
D7: รหัสพนักงาน / Code Staff / ID | F7: =+'ใบสรุป-68'!C6 -> 630617 | G7: =+'ใบสรุป-68'!D6 -> 1102002947799 | I7: วันที่/ Date
D8: แผนก / Department | F8: =+'ใบสรุป-68'!C7 -> Technician | I8: 01/01/2569
D9: ฝ่าย / Division | F9: =+'ใบสรุป-68'!C8 -> Factory | I9: เดือน/ For Month
D10: ตำแหน่ง / Position | F10: =+'ใบสรุป-68'!C9 -> Technician | I10: ธันวาคม /December
A11: ชื่อ - นามสกุล | B11: =+'ใบสรุป-68'!C4 -> Mr.Anuwat Surarit
A12: Name - Surname | B12: =+'ใบสรุป-68'!C5 -> นายอนุวัฒน์ สุราฤทธิ์
A14: รายการรับ | B14: เงินเดือน | C14: ค่าล่วงเวลา | D14: ค่าเบี้ยขยัน | E14: ค่าคอมมิชชั่น | F14: อื่น ๆ | G14: อื่น ๆ | I14: รวมเงินได้ทั้งสิ้น
A15: Income | B15: Salary | C15: Over time | E15: Commission | F15: Other | G15: Other | I15: Total Income
B16: =21895+750 -> 22645 | F16: 0 | G16: 0 | I16: =SUM(B16+C16+D16+E16+F16+G16) -> 22645
A18: รายการหัก | B18: ภาษี | C18: ประกันสังคม | D18: รายการ-อื่น ๆ | E18: อื่น ๆ | I18: รวมเงินหักทั้งสิ้น
A19: Reduction | B19: Income WHT | C19: Social Security Tax | D19: Other | E19: Other | I19: Total Reduction
B20: 0 | C20: 750 | D20: 0 | E20: 0 | I20: =+B20+C20+D20+E20 -> 750
A22: ยอดสะสม | B22: รายได้-สะสม | C22: ประกันสังคม-สะสม | D22: ภาษี-สะสม | E22: อื่น ๆ-สะสม | I22: รายได้สุทธิ
A23: Total Collection | B23: Collection Income | C23: Collection Social WHT | D23: Collection Income WHT | E23: Collection-Other | I23: Net Income
B24: =I16+'68-Nov'!B24 -> 269000 | C24: =C20+'68-Nov'!C24 -> 9000 | D24: =B20+'68-Nov'!D24 -> 0 | I24: =I16-I20 -> 21895

Sheet ด้านหลัง
A1: บริษัท ไอน์ชไตน์ อินดัสเตรียล เทคนิค คอร์ปอเรชั่น จำกัด
A2: (สนญ.) เลขที่ : 1/120 ซอยรามคำแหง 184 แขวงมีนบุรี เขตมีนบุรี กรุงเทพมหานคร 10510
A3: Tel : 0-2052-9544 Fax : 0-2052-9544 E-mail : sales@eitlaser.com
A14: (เอกสารฉบับนี้ถือเป็นความลับของบริษัท/ห้ามเผยแพร่)

Sheet ใบสรุป-68
A1: บริษัท ไอน์ชไตน์ อินดัสเตรียล เทคนิค คอร์ปอเรชั่น จำกัด (EIT)
A2: ใบสรุป-เงินเดือน
A3: ประจำปี 2568
A4: ชื่อ - นามสกุล | C4: Mr.Anuwat Surarit
A5: Name - Surname | C5: นายอนุวัฒน์ สุราฤทธิ์
A6: รหัสพนักงาน / Code Staff / ID | C6: 630617 | D6: 1102002947799
A7: แผนก / Department | C7: Technician
A8: ฝ่าย / Division | C8: Factory
A9: ตำแหน่ง / Position | C9: Technician
A10: วันที่เริ่มงาน | C10: 17/06/2563
A12: เดือน | B12: เงินเดือน | C12: ค่าล่วงเวลา | D12: ค่าเบี้ยขยัน | E12: ค่าคอมมิชชั่น | F12: อื่น ๆ | G12: อื่น ๆ | H12: Total | I12: อัตรา | J12: หัก ประกัน | K12: WHT-3% | L12: รับ-สุทธิ | M12: โอนเข้าบัญชี | O12: หมายเหตุ
B13: (บาท) | C13: Over time | E13: Commission | F13: Other | G13: (บาท) | H13: (บาท) | I13: SSO | J13: สังคม | K13: (บาท) | L13: (บาท) | M13: จำนวนเงิน (บาท) | N13: วันที่
A14: 2568
A15: มกราคม | B15: ='68-jan'!B16 -> 21709 | C15: ='68-jan'!C16 -> 0 | D15: ='68-jan'!D16 -> 0 | E15: ='68-jan'!E16 -> 0 | F15: ='68-jan'!F16 -> 0 | G15: ='68-jan'!G16 -> 0 | H15: =SUM(B15:G15) -> 21709 | I15: 5% | J15: =(15000)*I15 -> 750 | K15: =+-SUM(0)*3% -> 0 | L15: =H15-J15 -> 20959 | M15: =L15 -> 20959 | N15: 01/02/68
A16: กุมภาพันธ์ | B16: ='68-Feb'!B16 -> 21580 | C16: ='68-Feb'!C16 -> 0 | D16: ='68-Feb'!D16 -> 0 | E16: ='68-Feb'!E16 -> 0 | F16: ='68-Feb'!F16 -> 0 | G16: ='68-Feb'!G16 -> 0 | H16: =SUM(B16:G16) -> 21580 | I16: 5% | J16: =(15000)*I16 -> 750 | K16: =+-SUM(0)*3% -> 0 | L16: =H16-J16 -> 20830 | M16: =L16 -> 20830 | N16: 01/03/68
A17: มีนาคม | B17: ='68-Mar'!B16 -> 21428 | C17: ='68-Mar'!C16 -> 0 | D17: ='68-Mar'!D16 -> 0 | E17: ='68-Mar'!E16 -> 0 | F17: ='68-Mar'!F16 -> 0 | G17: ='68-Mar'!G16 -> 0 | H17: =SUM(B17:G17) -> 21428 | I17: 5% | J17: =(15000)*I17 -> 750 | K17: =+-SUM(0)*3% -> 0 | L17: =H17-J17 -> 20678 | M17: =L17 -> 20678 | N17: 01/04/68
A18: เมษายน | B18: ='68-Apr'!B16 -> 23161 | C18: ='68-Apr'!C16 -> 0 | D18: ='68-Apr'!D16 -> 0 | E18: ='68-Apr'!E16 -> 0 | F18: ='68-Apr'!F16 -> 0 | G18: ='68-Apr'!G16 -> 0 | H18: =SUM(B18:G18) -> 23161 | I18: 5% | J18: =(15000)*I18 -> 750 | K18: =+-SUM(0)*3% -> 0 | L18: =H18-J18 -> 22411 | M18: =L18 -> 22411 | N18: 01/05/68
A19: พฤษภาคม | B19: ='68-May'!B16 -> 22416 | C19: ='68-May'!C16 -> 0 | D19: ='68-May'!D16 -> 0 | E19: ='68-May'!E16 -> 0 | F19: ='68-May'!F16 -> 0 | G19: ='68-May'!G16 -> 0 | H19: =SUM(B19:G19) -> 22416 | I19: 5% | J19: =(15000)*I19 -> 750 | K19: =+-SUM(0)*3% -> 0 | L19: =H19-J19 -> 21666 | M19: =L19 -> 21666 | N19: 01/06/68
A20: มิถุนายน | B20: ='68-Jun'!B16 -> 23016 | C20: ='68-Jun'!C16 -> 0 | D20: ='68-Jun'!D16 -> 0 | E20: ='68-Jun'!E16 -> 0 | F20: ='68-Jun'!F16 -> 0 | G20: ='68-Jun'!G16 -> 0 | H20: =SUM(B20:G20) -> 23016 | I20: 5% | J20: =(15000)*I20 -> 750 | K20: =+-SUM(0)*3% -> 0 | L20: =H20-J20 -> 22266 | M20: =L20 -> 22266 | N20: 01/07/68
A21: กรกฎาคม | B21: ='68-Jul'!B16 -> 22750 | C21: ='68-Jul'!C16 -> 0 | D21: ='68-Jul'!D16 -> 0 | E21: ='68-Jul'!E16 -> 0 | F21: ='68-Jul'!F16 -> 0 | G21: ='68-Jul'!G16 -> 0 | H21: =SUM(B21:G21) -> 22750 | I21: 5% | J21: =(15000)*I21 -> 750 | K21: =+-SUM(0)*3% -> 0 | L21: =H21-J21 -> 22000 | M21: =L21 -> 22000 | N21: 01/08/68
A22: สิงหาคม | B22: ='68-Aug'!B16 -> 21684 | C22: ='68-Aug'!C16 -> 0 | D22: ='68-Aug'!D16 -> 0 | E22: ='68-Aug'!E16 -> 0 | F22: ='68-Aug'!F16 -> 0 | G22: ='68-Aug'!G16 -> 0 | H22: =SUM(B22:G22) -> 21684 | I22: 5% | J22: =(15000)*I22 -> 750 | K22: =+-SUM(0)*3% -> 0 | L22: =H22-J22 -> 20934 | M22: =L22 -> 20934 | N22: 01/09/68
A23: กันยายน | B23: ='68-Sep'!B16 -> 21735 | C23: ='68-Sep'!C16 -> 0 | D23: ='68-Sep'!D16 -> 0 | E23: ='68-Sep'!E16 -> 0 | F23: ='68-Sep'!F16 -> 0 | G23: ='68-Sep'!G16 -> 0 | H23: =SUM(B23:G23) -> 21735 | I23: 5% | J23: =(15000)*I23 -> 750 | K23: =+-SUM(0)*3% -> 0 | L23: =H23-J23 -> 20985 | M23: =L23 -> 20985 | N23: 01/10/68
A24: ตุลาคม | B24: ='68-Oct'!B16 -> 24093 | C24: ='68-Oct'!C16 -> 0 | D24: ='68-Oct'!D16 -> 0 | E24: ='68-Oct'!E16 -> 0 | F24: ='68-Oct'!F16 -> 0 | G24: ='68-Oct'!G16 -> 0 | H24: =SUM(B24:G24) -> 24093 | I24: 5% | J24: =(15000)*I24 -> 750 | K24: =+-SUM(0)*3% -> 0 | L24: =H24-J24 -> 23343 | M24: =L24 -> 23343 | N24: 01/11/68
A25: พฤศจิกายน | B25: ='68-Nov'!B16 -> 22783 | C25: ='68-Nov'!C16 -> 0 | D25: ='68-Nov'!D16 -> 0 | E25: ='68-Nov'!E16 -> 0 | F25: ='68-Nov'!F16 -> 0 | G25: ='68-Nov'!G16 -> 0 | H25: =SUM(B25:G25) -> 22783 | I25: 5% | J25: =(15000)*I25 -> 750 | K25: =+-SUM(0)*3% -> 0 | L25: =H25-J25 -> 22033 | M25: =L25 -> 22033 | N25: 01/12/68
A26: ธันวาคม | B26: ='68-Dec'!B16 -> 22645 | C26: ='68-Dec'!C16 -> 0 | D26: ='68-Dec'!D16 -> 0 | E26: ='68-Dec'!E16 -> 0 | F26: ='68-Dec'!F16 -> 0 | G26: ='68-Dec'!G16 -> 0 | H26: =SUM(B26:G26) -> 22645 | I26: 5% | J26: =(15000)*I26 -> 750 | K26: =+-SUM(0)*3% -> 0 | L26: =H26-J26 -> 21895 | M26: =L26 -> 21895 | N26: 01/01/69
A28: รวม | B28: =SUM(B15:B27) -> 269000 | C28: =SUM(C15:C27) -> 0 | D28: =SUM(D15:D27) -> 0 | E28: =SUM(E15:E27) -> 0 | F28: =SUM(F15:F27) -> 0 | G28: =SUM(G15:G27) -> 0 | H28: =SUM(H15:H27) -> 269000 | J28: =SUM(J15:J27) -> 9000 | K28: =SUM(K15:K27) -> 0 | L28: =SUM(L15:L27) -> 260000 | M28: =SUM(M15:M27) -> 260000
