Workbook

Sheet 69-jan
A1: บริษัท ไอน์ชไตน์ อินดัสเตรียล เทคนิค คอร์ปอเรชั่น จำกัด
A2: (สำนักงานใหญ่) เลขที่ : 1/120 ซอยรามคำแหง 184 แขวงมีนบุรี เขตมีนบุรี กรุงเทพมหานคร 10510
A3: Tel : 0-2052-9544 Fax : 0-2052-9544 E-mail : sales@eitlaser.com
A5: ใบจ่ายเงินเดือน / Pay Slip
D7: รหัสพนักงาน / Code Staff / ID | F7: =+'ใบสรุป-69'!C6 -> 650321 | G7: =+'ใบสรุป-69'!D6 -> 1209000128664 | I7: วันที่/ Date
D8: แผนก / Department | F8: =+'ใบสรุป-69'!C7 -> Technician | I8: 01/02/2569
D9: ฝ่าย / Division | F9: =+'ใบสรุป-69'!C8 -> Factory | I9: เดือน/ For Month
D10: ตำแหน่ง / Position | F10: =+'ใบสรุป-69'!C9 -> Technician | I10: มกราคม /January
A11: ชื่อ - นามสกุล | B11: =+'ใบสรุป-69'!C4 -> Mr.Nakharin Angkapanompai
A12: Name - Surname | B12: =+'ใบสรุป-69'!C5 -> นายนครินทร์ อังคะพนมไพร
A14: รายการรับ | B14: เงินเดือน | C14: ค่าล่วงเวลา | D14: ค่าเบี้ยขยัน | E14: ค่าคอมมิชชั่น | F14: อื่น ๆ | G14: อื่น ๆ | I14: รวมเงินได้ทั้งสิ้น
A15: Income | B15: Salary | C15: Over time | E15: Commission | F15: Other | G15: Other | I15: Total Income
F16: 0 | G16: 0 | I16: =SUM(B16+C16+D16+E16+F16+G16) -> 0
A18: รายการหัก | B18: ภาษี | C18: ประกันสังคม | D18: รายการ-อื่น ๆ | E18: อื่น ๆ | I18: รวมเงินหักทั้งสิ้น
A19: Reduction | B19: Income WHT | C19: Social Security Tax | D19: Other | E19: Other | I19: Total Reduction
B20: 0 | C20: 875 | D20: 0 | E20: 0 | I20: =+B20+C20+D20+E20 -> 875
A22: ยอดสะสม | B22: รายได้-สะสม | C22: ประกันสังคม-สะสม | D22: ภาษี-สะสม | E22: อื่น ๆ-สะสม | I22: รายได้สุทธิ
A23: Total Collection | B23: Collection Income | C23: Collection Social WHT | D23: Collection Income WHT | E23: Collection-Other | I23: Net Income
B24: =I16 -> 0 | C24: =C20 -> 875 | D24: =B20 -> 0 | E24: =F16+G16+D20+E20 -> 0 | I24: =+I16-I20 -> -875

Sheet 69-Feb
A1: บริษัท ไอน์ชไตน์ อินดัสเตรียล เทคนิค คอร์ปอเรชั่น จำกัด
A2: (สำนักงานใหญ่) เลขที่ : 1/120 ซอยรามคำแหง 184 แขวงมีนบุรี เขตมีนบุรี กรุงเทพมหานคร 10510
A3: Tel : 0-2052-9544 Fax : 0-2052-9544 E-mail : sales@eitlaser.com
A5: ใบจ่ายเงินเดือน / Pay Slip
D7: รหัสพนักงาน / Code Staff / ID | F7: =+'ใบสรุป-69'!C6 -> 650321 | G7: =+'ใบสรุป-69'!D6 -> 1209000128664 | I7: วันที่/ Date
D8: แผนก / Department | F8: =+'ใบสรุป-69'!C7 -> Technician | I8: 01/03/2569
D9: ฝ่าย / Division | F9: =+'ใบสรุป-69'!C8 -> Factory | I9: เดือน/ For Month
D10: ตำแหน่ง / Position | F10: =+'ใบสรุป-69'!C9 -> Technician | I10: กุมภาพันธ์ /February
A11: ชื่อ - นามสกุล | B11: =+'ใบสรุป-69'!C4 -> Mr.Nakharin Angkapanompai
A12: Name - Surname | B12: =+'ใบสรุป-69'!C5 -> นายนครินทร์ อังคะพนมไพร
A14: รายการรับ | B14: เงินเดือน | C14: ค่าล่วงเวลา | D14: ค่าเบี้ยขยัน | E14: ค่าคอมมิชชั่น | F14: อื่น ๆ | G14: อื่น ๆ | I14: รวมเงินได้ทั้งสิ้น
A15: Income | B15: Salary | C15: Over time | E15: Commission | F15: Other | G15: Other | I15: Total Income
F16: 0 | G16: 0 | I16: =SUM(B16+C16+D16+E16+F16+G16) -> 0
A18: รายการหัก | B18: ภาษี | C18: ประกันสังคม | D18: รายการ-อื่น ๆ | E18: อื่น ๆ | I18: รวมเงินหักทั้งสิ้น
A19: Reduction | B19: Income WHT | C19: Social Security Tax | D19: Other | E19: Other | I19: Total Reduction
B20: 0 | C20: 875 | D20: 0 | E20: 0 | I20: =+B20+C20+D20+E20 -> 875
A22: ยอดสะสม | B22: รายได้-สะสม | C22: ประกันสังคม-สะสม | D22: ภาษี-สะสม | E22: อื่น ๆ-สะสม | I22: รายได้สุทธิ
A23: Total Collection | B23: Collection Income | C23: Collection Social WHT | D23: Collection Income WHT | E23: Collection-Other | I23: Net Income
B24: =I16+'69-jan'!B24 -> 0 | C24: =C20+'69-jan'!C24 -> 1750 | D24: =B20+'69-jan'!D24 -> 0 | I24: =I16-I20 -> -875

Sheet 69-Mar
A1: บริษัท ไอน์ชไตน์ อินดัสเตรียล เทคนิค คอร์ปอเรชั่น จำกัด
A2: (สำนักงานใหญ่) เลขที่ : 1/120 ซอยรามคำแหง 184 แขวงมีนบุรี เขตมีนบุรี กรุงเทพมหานคร 10510
A3: Tel : 0-2052-9544 Fax : 0-2052-9544 E-mail : sales@eitlaser.com
A5: ใบจ่ายเงินเดือน / Pay Slip
D7: รหัสพนักงาน / Code Staff / ID | F7: =+'ใบสรุป-69'!C6 -> 650321 | G7: =+'ใบสรุป-69'!D6 -> 1209000128664 | I7: วันที่/ Date
D8: แผนก / Department | F8: =+'ใบสรุป-69'!C7 -> Technician | I8: 01/04/2569
D9: ฝ่าย / Division | F9: =+'ใบสรุป-69'!C8 -> Factory | I9: เดือน/ For Month
D10: ตำแหน่ง / Position | F10: =+'ใบสรุป-69'!C9 -> Technician | I10: มีนาคม /March
A11: ชื่อ - นามสกุล | B11: =+'ใบสรุป-69'!C4 -> Mr.Nakharin Angkapanompai
A12: Name - Surname | B12: =+'ใบสรุป-69'!C5 -> นายนครินทร์ อังคะพนมไพร
A14: รายการรับ | B14: เงินเดือน | C14: ค่าล่วงเวลา | D14: ค่าเบี้ยขยัน | E14: ค่าคอมมิชชั่น | F14: อื่น ๆ | G14: อื่น ๆ | I14: รวมเงินได้ทั้งสิ้น
A15: Income | B15: Salary | C15: Over time | E15: Commission | F15: Other | G15: Other | I15: Total Income
F16: 0 | G16: 0 | I16: =SUM(B16+C16+D16+E16+F16+G16) -> 0
A18: รายการหัก | B18: ภาษี | C18: ประกันสังคม | D18: รายการ-อื่น ๆ | E18: อื่น ๆ | I18: รวมเงินหักทั้งสิ้น
A19: Reduction | B19: Income WHT | C19: Social Security Tax | D19: Other | E19: Other | I19: Total Reduction
B20: 0 | C20: 875 | D20: 0 | E20: 0 | I20: =+B20+C20+D20+E20 -> 875
A22: ยอดสะสม | B22: รายได้-สะสม | C22: ประกันสังคม-สะสม | D22: ภาษี-สะสม | E22: อื่น ๆ-สะสม | I22: รายได้สุทธิ
A23: Total Collection | B23: Collection Income | C23: Collection Social WHT | D23: Collection Income WHT | E23: Collection-Other | I23: Net Income
B24: =I16+'69-Feb'!B24 -> 0 | C24: =C20+'69-Feb'!C24 -> 2625 | D24: =B20+'69-Feb'!D24 -> 0 | I24: =+I16-I20 -> -875

Sheet 69-Apr
A1: บริษัท ไอน์ชไตน์ อินดัสเตรียล เทคนิค คอร์ปอเรชั่น จำกัด
A2: (สำนักงานใหญ่) เลขที่ : 1/120 ซอยรามคำแหง 184 แขวงมีนบุรี เขตมีนบุรี กรุงเทพมหานคร 10510
A3: Tel : 0-2052-9544 Fax : 0-2052-9544 E-mail : sales@eitlaser.com
A5: ใบจ่ายเงินเดือน / Pay Slip
D7: รหัสพนักงาน / Code Staff / ID | F7: =+'ใบสรุป-69'!C6 -> 650321 | G7: =+'ใบสรุป-69'!D6 -> 1209000128664 | I7: วันที่/ Date
D8: แผนก / Department | F8: =+'ใบสรุป-69'!C7 -> Technician | I8: 01/05/2569
D9: ฝ่าย / Division | F9: =+'ใบสรุป-69'!C8 -> Factory | I9: เดือน/ For Month
D10: ตำแหน่ง / Position | F10: =+'ใบสรุป-69'!C9 -> Technician | I10: เมษายน /April
A11: ชื่อ - นามสกุล | B11: =+'ใบสรุป-69'!C4 -> Mr.Nakharin Angkapanompai
A12: Name - Surname | B12: =+'ใบสรุป-69'!C5 -> นายนครินทร์ อังคะพนมไพร
A14: รายการรับ | B14: เงินเดือน | C14: ค่าล่วงเวลา | D14: ค่าเบี้ยขยัน | E14: ค่าคอมมิชชั่น | F14: อื่น ๆ | G14: อื่น ๆ | I14: รวมเงินได้ทั้งสิ้น
A15: Income | B15: Salary | C15: Over time | E15: Commission | F15: Other | G15: Other | I15: Total Income
F16: 0 | G16: 0 | I16: =SUM(B16+C16+D16+E16+F16+G16) -> 0
A18: รายการหัก | B18: ภาษี | C18: ประกันสังคม | D18: รายการ-อื่น ๆ | E18: อื่น ๆ | I18: รวมเงินหักทั้งสิ้น
A19: Reduction | B19: Income WHT | C19: Social Security Tax | D19: Other | E19: Other | I19: Total Reduction
B20: 0 | C20: 875 | D20: 0 | E20: 0 | I20: =+B20+C20+D20+E20 -> 875
A22: ยอดสะสม | B22: รายได้-สะสม | C22: ประกันสังคม-สะสม | D22: ภาษี-สะสม | E22: อื่น ๆ-สะสม | I22: รายได้สุทธิ
A23: Total Collection | B23: Collection Income | C23: Collection Social WHT | D23: Collection Income WHT | E23: Collection-Other | I23: Net Income
B24: =I16+'69-Mar'!B24 -> 0 | C24: =C20+'69-Mar'!C24 -> 3500 | D24: =B20+'69-Mar'!D24 -> 0 | I24: =+I16-I20 -> -875

Sheet 69-May
A1: บริษัท ไอน์ชไตน์ อินดัสเตรียล เทคนิค คอร์ปอเรชั่น จำกัด
A2: (สำนักงานใหญ่) เลขที่ : 1/120 ซอยรามคำแหง 184 แขวงมีนบุรี เขตมีนบุรี กรุงเทพมหานคร 10510
A3: Tel : 0-2052-9544 Fax : 0-2052-9544 E-mail : sales@eitlaser.com
A5: ใบจ่ายเงินเดือน / Pay Slip
D7: รหัสพนักงาน / Code Staff / ID | F7: =+'ใบสรุป-69'!C6 -> 650321 | G7: =+'ใบสรุป-69'!D6 -> 1209000128664 | I7: วันที่/ Date
D8: แผนก / Department | F8: =+'ใบสรุป-69'!C7 -> Technician | I8: 01/06/2569
D9: ฝ่าย / Division | F9: =+'ใบสรุป-69'!C8 -> Factory | I9: เดือน/ For Month
D10: ตำแหน่ง / Position | F10: =+'ใบสรุป-69'!C9 -> Technician | I10: พฤษภาคม /May
A11: ชื่อ - นามสกุล | B11: =+'ใบสรุป-69'!C4 -> Mr.Nakharin Angkapanompai
A12: Name - Surname | B12: =+'ใบสรุป-69'!C5 -> นายนครินทร์ อังคะพนมไพร
A14: รายการรับ | B14: เงินเดือน | C14: ค่าล่วงเวลา | D14: ค่าเบี้ยขยัน | E14: ค่าคอมมิชชั่น | F14: อื่น ๆ | G14: อื่น ๆ | I14: รวมเงินได้ทั้งสิ้น
A15: Income | B15: Salary | C15: Over time | E15: Commission | F15: Other | G15: Other | I15: Total Income
F16: 0 | G16: 0 | I16: =SUM(B16+C16+D16+E16+F16+G16) -> 0
A18: รายการหัก | B18: ภาษี | C18: ประกันสังคม | D18: รายการ-อื่น ๆ | E18: อื่น ๆ | I18: รวมเงินหักทั้งสิ้น
A19: Reduction | B19: Income WHT | C19: Social Security Tax | D19: Other | E19: Other | I19: Total Reduction
B20: 0 | C20: 875 | D20: 0 | E20: 0 | I20: =+B20+C20+D20+E20 -> 875
A22: ยอดสะสม | B22: รายได้-สะสม | C22: ประกันสังคม-สะสม | D22: ภาษี-สะสม | E22: อื่น ๆ-สะสม | I22: รายได้สุทธิ
A23: Total Collection | B23: Collection Income | C23: Collection Social WHT | D23: Collection Income WHT | E23: Collection-Other | I23: Net Income
B24: =I16+'69-Apr'!B24 -> 0 | C24: =C20+'69-Apr'!C24 -> 4375 | D24: =B20+'69-Apr'!D24 -> 0 | I24: =+I16-I20 -> -875

Sheet 69-Jun
A1: บริษัท ไอน์ชไตน์ อินดัสเตรียล เทคนิค คอร์ปอเรชั่น จำกัด
A2: (สำนักงานใหญ่) เลขที่ : 1/120 ซอยรามคำแหง 184 แขวงมีนบุรี เขตมีนบุรี กรุงเทพมหานคร 10510
A3: Tel : 0-2052-9544 Fax : 0-2052-9544 E-mail : sales@eitlaser.com
A5: ใบจ่ายเงินเดือน / Pay Slip
D7: รหัสพนักงาน / Code Staff / ID | F7: =+'ใบสรุป-69'!C6 -> 650321 | G7: =+'ใบสรุป-69'!D6 -> 1209000128664 | I7: วันที่/ Date
D8: แผนก / Department | F8: =+'ใบสรุป-69'!C7 -> Technician | I8: 01/07/2569
D9: ฝ่าย / Division | F9: =+'ใบสรุป-69'!C8 -> Factory | I9: เดือน/ For Month
D10: ตำแหน่ง / Position | F10: =+'ใบสรุป-69'!C9 -> Technician | I10: มิถุนายน /June
A11: ชื่อ - นามสกุล | B11: =+'ใบสรุป-69'!C4 -> Mr.Nakharin Angkapanompai
A12: Name - Surname | B12: =+'ใบสรุป-69'!C5 -> นายนครินทร์ อังคะพนมไพร
A14: รายการรับ | B14: เงินเดือน | C14: ค่าล่วงเวลา | D14: ค่าเบี้ยขยัน | E14: ค่าคอมมิชชั่น | F14: อื่น ๆ | G14: อื่น ๆ | I14: รวมเงินได้ทั้งสิ้น
A15: Income | B15: Salary | C15: Over time | E15: Commission | F15: Other | G15: Other | I15: Total Income
F16: 0 | G16: 0 | I16: =SUM(B16+C16+D16+E16+F16+G16) -> 0
A18: รายการหัก | B18: ภาษี | C18: ประกันสังคม | D18: รายการ-อื่น ๆ | E18: อื่น ๆ | I18: รวมเงินหักทั้งสิ้น
A19: Reduction | B19: Income WHT | C19: Social Security Tax | D19: Other | E19: Other | I19: Total Reduction
B20: 0 | C20: 875 | D20: 0 | E20: 0 | I20: =+B20+C20+D20+E20 -> 875
A22: ยอดสะสม | B22: รายได้-สะสม | C22: ประกันสังคม-สะสม | D22: ภาษี-สะสม | E22: อื่น ๆ-สะสม | I22: รายได้สุทธิ
A23: Total Collection | B23: Collection Income | C23: Collection Social WHT | D23: Collection Income WHT | E23: Collection-Other | I23: Net Income
B24: =I16+'69-May'!B24 -> 0 | C24: =C20+'69-May'!C24 -> 5250 | D24: =B20+'69-May'!D24 -> 0 | I24: =+I16-I20 -> -875

Sheet 69-Jul
A1: บริษัท ไอน์ชไตน์ อินดัสเตรียล เทคนิค คอร์ปอเรชั่น จำกัด
A2: (สำนักงานใหญ่) เลขที่ : 1/120 ซอยรามคำแหง 184 แขวงมีนบุรี เขตมีนบุรี กรุงเทพมหานคร 10510
A3: Tel : 0-2052-9544 Fax : 0-2052-9544 E-mail : sales@eitlaser.com
A5: ใบจ่ายเงินเดือน / Pay Slip
D7: รหัสพนักงาน / Code Staff / ID | F7: =+'ใบสรุป-69'!C6 -> 650321 | G7: =+'ใบสรุป-69'!D6 -> 1209000128664 | I7: วันที่/ Date
D8: แผนก / Department | F8: =+'ใบสรุป-69'!C7 -> Technician | I8: 01/08/2569
D9: ฝ่าย / Division | F9: =+'ใบสรุป-69'!C8 -> Factory | I9: เดือน/ For Month
D10: ตำแหน่ง / Position | F10: =+'ใบสรุป-69'!C9 -> Technician | I10: กรกฎาคม /July
A11: ชื่อ - นามสกุล | B11: =+'ใบสรุป-69'!C4 -> Mr.Nakharin Angkapanompai
A12: Name - Surname | B12: =+'ใบสรุป-69'!C5 -> นายนครินทร์ อังคะพนมไพร
A14: รายการรับ | B14: เงินเดือน | C14: ค่าล่วงเวลา | D14: ค่าเบี้ยขยัน | E14: ค่าคอมมิชชั่น | F14: อื่น ๆ | G14: อื่น ๆ | I14: รวมเงินได้ทั้งสิ้น
A15: Income | B15: Salary | C15: Over time | E15: Commission | F15: Other | G15: Other | I15: Total Income
F16: 0 | G16: 0 | I16: =SUM(B16+C16+D16+E16+F16+G16) -> 0
A18: รายการหัก | B18: ภาษี | C18: ประกันสังคม | D18: รายการ-อื่น ๆ | E18: อื่น ๆ | I18: รวมเงินหักทั้งสิ้น
A19: Reduction | B19: Income WHT | C19: Social Security Tax | D19: Other | E19: Other | I19: Total Reduction
B20: 0 | C20: 875 | D20: 0 | E20: 0 | I20: =+B20+C20+D20+E20 -> 875
A22: ยอดสะสม | B22: รายได้-สะสม | C22: ประกันสังคม-สะสม | D22: ภาษี-สะสม | E22: อื่น ๆ-สะสม | I22: รายได้สุทธิ
A23: Total Collection | B23: Collection Income | C23: Collection Social WHT | D23: Collection Income WHT | E23: Collection-Other | I23: Net Income
B24: =I16+'69-Jun'!B24 -> 0 | C24: =C20+'69-Jun'!C24 -> 6125 | D24: =B20+'69-Jun'!D24 -> 0 | I24: =+I16-I20 -> -875

Sheet 69-Aug
A1: บริษัท ไอน์ชไตน์ อินดัสเตรียล เทคนิค คอร์ปอเรชั่น จำกัด
A2: (สำนักงานใหญ่) เลขที่ : 1/120 ซอยรามคำแหง 184 แขวงมีนบุรี เขตมีนบุรี กรุงเทพมหานคร 10510
A3: Tel : 0-2052-9544 Fax : 0-2052-9544 E-mail : sales@eitlaser.com
A5: ใบจ่ายเงินเดือน / Pay Slip
D7: รหัสพนักงาน / Code Staff / ID | F7: =+'ใบสรุป-69'!C6 -> 650321 | G7: =+'ใบสรุป-69'!D6 -> 1209000128664 | I7: วันที่/ Date
D8: แผนก / Department | F8: =+'ใบสรุป-69'!C7 -> Technician | I8: 01/09/2569
D9: ฝ่าย / Division | F9: =+'ใบสรุป-69'!C8 -> Factory | I9: เดือน/ For Month
D10: ตำแหน่ง / Position | F10: =+'ใบสรุป-69'!C9 -> Technician | I10: สิงหาคม /August
A11: ชื่อ - นามสกุล | B11: =+'ใบสรุป-69'!C4 -> Mr.Nakharin Angkapanompai
A12: Name - Surname | B12: =+'ใบสรุป-69'!C5 -> นายนครินทร์ อังคะพนมไพร
A14: รายการรับ | B14: เงินเดือน | C14: ค่าล่วงเวลา | D14: ค่าเบี้ยขยัน | E14: ค่าคอมมิชชั่น | F14: อื่น ๆ | G14: อื่น ๆ | I14: รวมเงินได้ทั้งสิ้น
A15: Income | B15: Salary | C15: Over time | E15: Commission | F15: Other | G15: Other | I15: Total Income
F16: 0 | G16: 0 | I16: =SUM(B16+C16+D16+E16+F16+G16) -> 0
A18: รายการหัก | B18: ภาษี | C18: ประกันสังคม | D18: รายการ-อื่น ๆ | E18: อื่น ๆ | I18: รวมเงินหักทั้งสิ้น
A19: Reduction | B19: Income WHT | C19: Social Security Tax | D19: Other | E19: Other | I19: Total Reduction
B20: 0 | C20: 875 | D20: 0 | E20: 0 | I20: =+B20+C20+D20+E20 -> 875
A22: ยอดสะสม | B22: รายได้-สะสม | C22: ประกันสังคม-สะสม | D22: ภาษี-สะสม | E22: อื่น ๆ-สะสม | I22: รายได้สุทธิ
A23: Total Collection | B23: Collection Income | C23: Collection Social WHT | D23: Collection Income WHT | E23: Collection-Other | I23: Net Income
B24: =I16+'69-Jul'!B24 -> 0 | C24: =C20+'69-Jul'!C24 -> 7000 | D24: =B20+'69-Jul'!D24 -> 0 | I24: =+I16-I20 -> -875

Sheet 69-Sep
A1: บริษัท ไอน์ชไตน์ อินดัสเตรียล เทคนิค คอร์ปอเรชั่น จำกัด
A2: (สำนักงานใหญ่) เลขที่ : 1/120 ซอยรามคำแหง 184 แขวงมีนบุรี เขตมีนบุรี กรุงเทพมหานคร 10510
A3: Tel : 0-2052-9544 Fax : 0-2052-9544 E-mail : sales@eitlaser.com
A5: ใบจ่ายเงินเดือน / Pay Slip
D7: รหัสพนักงาน / Code Staff / ID | F7: =+'ใบสรุป-69'!C6 -> 650321 | G7: =+'ใบสรุป-69'!D6 -> 1209000128664 | I7: วันที่/ Date
D8: แผนก / Department | F8: =+'ใบสรุป-69'!C7 -> Technician | I8: 01/10/2569
D9: ฝ่าย / Division | F9: =+'ใบสรุป-69'!C8 -> Factory | I9: เดือน/ For Month
D10: ตำแหน่ง / Position | F10: =+'ใบสรุป-69'!C9 -> Technician | I10: กันยายน /September
A11: ชื่อ - นามสกุล | B11: =+'ใบสรุป-69'!C4 -> Mr.Nakharin Angkapanompai
A12: Name - Surname | B12: =+'ใบสรุป-69'!C5 -> นายนครินทร์ อังคะพนมไพร
A14: รายการรับ | B14: เงินเดือน | C14: ค่าล่วงเวลา | D14: ค่าเบี้ยขยัน | E14: ค่าคอมมิชชั่น | F14: อื่น ๆ | G14: อื่น ๆ | I14: รวมเงินได้ทั้งสิ้น
A15: Income | B15: Salary | C15: Over time | E15: Commission | F15: Other | G15: Other | I15: Total Income
F16: 0 | G16: 0 | I16: =SUM(B16+C16+D16+E16+F16+G16) -> 0
A18: รายการหัก | B18: ภาษี | C18: ประกันสังคม | D18: รายการ-อื่น ๆ | E18: อื่น ๆ | I18: รวมเงินหักทั้งสิ้น
A19: Reduction | B19: Income WHT | C19: Social Security Tax | D19: Other | E19: Other | I19: Total Reduction
B20: 0 | C20: 875 | D20: 0 | E20: 0 | I20: =+B20+C20+D20+E20 -> 875
A22: ยอดสะสม | B22: รายได้-สะสม | C22: ประกันสังคม-สะสม | D22: ภาษี-สะสม | E22: อื่น ๆ-สะสม | I22: รายได้สุทธิ
A23: Total Collection | B23: Collection Income | C23: Collection Social WHT | D23: Collection Income WHT | E23: Collection-Other | I23: Net Income
B24: =I16+'69-Aug'!B24 -> 0 | C24: =C20+'69-Aug'!C24 -> 7875 | D24: =B20+'69-Aug'!D24 -> 0 | I24: =+I16-I20 -> -875

Sheet 69-Oct
A1: บริษัท ไอน์ชไตน์ อินดัสเตรียล เทคนิค คอร์ปอเรชั่น จำกัด
A2: (สำนักงานใหญ่) เลขที่ : 1/120 ซอยรามคำแหง 184 แขวงมีนบุรี เขตมีนบุรี กรุงเทพมหานคร 10510
A3: Tel : 0-2052-9544 Fax : 0-2052-9544 E-mail : sales@eitlaser.com
A5: ใบจ่ายเงินเดือน / Pay Slip
D7: รหัสพนักงาน / Code Staff / ID | F7: =+'ใบสรุป-69'!C6 -> 650321 | G7: =+'ใบสรุป-69'!D6 -> 1209000128664 | I7: วันที่/ Date
D8: แผนก / Department | F8: =+'ใบสรุป-69'!C7 -> Technician | I8: 01/11/2569
D9: ฝ่าย / Division | F9: =+'ใบสรุป-69'!C8 -> Factory | I9: เดือน/ For Month
D10: ตำแหน่ง / Position | F10: =+'ใบสรุป-69'!C9 -> Technician | I10: ตุลาคม /October
A11: ชื่อ - นามสกุล | B11: =+'ใบสรุป-69'!C4 -> Mr.Nakharin Angkapanompai
A12: Name - Surname | B12: =+'ใบสรุป-69'!C5 -> นายนครินทร์ อังคะพนมไพร
A14: รายการรับ | B14: เงินเดือน | C14: ค่าล่วงเวลา | D14: ค่าเบี้ยขยัน | E14: ค่าคอมมิชชั่น | F14: อื่น ๆ | G14: อื่น ๆ | I14: รวมเงินได้ทั้งสิ้น
A15: Income | B15: Salary | C15: Over time | E15: Commission | F15: Other | G15: Other | I15: Total Income
F16: 0 | G16: 0 | I16: =SUM(B16+C16+D16+E16+F16+G16) -> 0
A18: รายการหัก | B18: ภาษี | C18: ประกันสังคม | D18: รายการ-อื่น ๆ | E18: อื่น ๆ | I18: รวมเงินหักทั้งสิ้น
A19: Reduction | B19: Income WHT | C19: Social Security Tax | D19: Other | E19: Other | I19: Total Reduction
B20: 0 | C20: 875 | D20: 0 | E20: 0 | I20: =+B20+C20+D20+E20 -> 875
A22: ยอดสะสม | B22: รายได้-สะสม | C22: ประกันสังคม-สะสม | D22: ภาษี-สะสม | E22: อื่น ๆ-สะสม | I22: รายได้สุทธิ
A23: Total Collection | B23: Collection Income | C23: Collection Social WHT | D23: Collection Income WHT | E23: Collection-Other | I23: Net Income
B24: =I16+'69-Sep'!B24 -> 0 | C24: =C20+'69-Sep'!C24 -> 8750 | D24: =B20+'69-Sep'!D24 -> 0 | I24: =+I16-I20 -> -875

Sheet 69-Nov
A1: บริษัท ไอน์ชไตน์ อินดัสเตรียล เทคนิค คอร์ปอเรชั่น จำกัด
A2: (สำนักงานใหญ่) เลขที่ : 1/120 ซอยรามคำแหง 184 แขวงมีนบุรี เขตมีนบุรี กรุงเทพมหานคร 10510
A3: Tel : 0-2052-9544 Fax : 0-2052-9544 E-mail : sales@eitlaser.com
A5: ใบจ่ายเงินเดือน / Pay Slip
D7: รหัสพนักงาน / Code Staff / ID | F7: =+'ใบสรุป-69'!C6 -> 650321 | G7: =+'ใบสรุป-69'!D6 -> 1209000128664 | I7: วันที่/ Date
D8: แผนก / Department | F8: =+'ใบสรุป-69'!C7 -> Technician | I8: 01/12/2569
D9: ฝ่าย / Division | F9: =+'ใบสรุป-69'!C8 -> Factory | I9: เดือน/ For Month
D10: ตำแหน่ง / Position | F10: =+'ใบสรุป-69'!C9 -> Technician | I10: พฤศจิกายน /November
A11: ชื่อ - นามสกุล | B11: =+'ใบสรุป-69'!C4 -> Mr.Nakharin Angkapanompai
A12: Name - Surname | B12: =+'ใบสรุป-69'!C5 -> นายนครินทร์ อังคะพนมไพร
A14: รายการรับ | B14: เงินเดือน | C14: ค่าล่วงเวลา | D14: ค่าเบี้ยขยัน | E14: ค่าคอมมิชชั่น | F14: อื่น ๆ | G14: อื่น ๆ | I14: รวมเงินได้ทั้งสิ้น
A15: Income | B15: Salary | C15: Over time | E15: Commission | F15: Other | G15: Other | I15: Total Income
F16: 0 | G16: 0 | I16: =SUM(B16+C16+D16+E16+F16+G16) -> 0
A18: รายการหัก | B18: ภาษี | C18: ประกันสังคม | D18: รายการ-อื่น ๆ | E18: อื่น ๆ | I18: รวมเงินหักทั้งสิ้น
A19: Reduction | B19: Income WHT | C19: Social Security Tax | D19: Other | E19: Other | I19: Total Reduction
B20: 0 | C20: 875 | D20: 0 | E20: 0 | I20: =+B20+C20+D20+E20 -> 875
A22: ยอดสะสม | B22: รายได้-สะสม | C22: ประกันสังคม-สะสม | D22: ภาษี-สะสม | E22: อื่น ๆ-สะสม | I22: รายได้สุทธิ
A23: Total Collection | B23: Collection Income | C23: Collection Social WHT | D23: Collection Income WHT | E23: Collection-Other | I23: Net Income
B24: =I16+'69-Oct'!B24 -> 0 | C24: =C20+'69-Oct'!C24 -> 9625 | D24: =B20+'69-Oct'!D24 -> 0 | I24: =+I16-I20 -> -875

Sheet 69-Dec
A1: บริษัท ไอน์ชไตน์ อินดัสเตรียล เทคนิค คอร์ปอเรชั่น จำกัด
A2: (สำนักงานใหญ่) เลขที่ : 1/120 ซอยรามคำแหง 184 แขวงมีนบุรี เขตมีนบุรี กรุงเทพมหานคร 10510
A3: Tel : 0-2052-9544 Fax : 0-2052-9544 E-mail : sales@eitlaser.com
A5: ใบจ่ายเงินเดือน / Pay Slip
D7: รหัสพนักงาน / Code Staff / ID | F7: =+'ใบสรุป-69'!C6 -> 650321 | G7: =+'ใบสรุป-69'!D6 -> 1209000128664 | I7: วันที่/ Date
D8: แผนก / Department | F8: =+'ใบสรุป-69'!C7 -> Technician | I8: 01/01/2570
D9: ฝ่าย / Division | F9: =+'ใบสรุป-69'!C8 -> Factory | I9: เดือน/ For Month
D10: ตำแหน่ง / Position | F10: =+'ใบสรุป-69'!C9 -> Technician | I10: ธันวาคม /December
A11: ชื่อ - นามสกุล | B11: =+'ใบสรุป-69'!C4 -> Mr.Nakharin Angkapanompai
A12: Name - Surname | B12: =+'ใบสรุป-69'!C5 -> นายนครินทร์ อังคะพนมไพร
A14: รายการรับ | B14: เงินเดือน | C14: ค่าล่วงเวลา | D14: ค่าเบี้ยขยัน | E14: ค่าคอมมิชชั่น | F14: อื่น ๆ | G14: อื่น ๆ | I14: รวมเงินได้ทั้งสิ้น
A15: Income | B15: Salary | C15: Over time | E15: Commission | F15: Other | G15: Other | I15: Total Income
F16: 0 | G16: 0 | I16: =SUM(B16+C16+D16+E16+F16+G16) -> 0
A18: รายการหัก | B18: ภาษี | C18: ประกันสังคม | D18: รายการ-อื่น ๆ | E18: อื่น ๆ | I18: รวมเงินหักทั้งสิ้น
A19: Reduction | B19: Income WHT | C19: Social Security Tax | D19: Other | E19: Other | I19: Total Reduction
B20: 0 | C20: 875 | D20: 0 | E20: 0 | I20: =+B20+C20+D20+E20 -> 875
A22: ยอดสะสม | B22: รายได้-สะสม | C22: ประกันสังคม-สะสม | D22: ภาษี-สะสม | E22: อื่น ๆ-สะสม | I22: รายได้สุทธิ
A23: Total Collection | B23: Collection Income | C23: Collection Social WHT | D23: Collection Income WHT | E23: Collection-Other | I23: Net Income
B24: =I16+'69-Nov'!B24 -> 0 | C24: =C20+'69-Nov'!C24 -> 10500 | D24: =B20+'69-Nov'!D24 -> 0 | I24: =I16-I20 -> -875

Sheet ด้านหลัง
A1: บริษัท ไอน์ชไตน์ อินดัสเตรียล เทคนิค คอร์ปอเรชั่น จำกัด
A2: (สนญ.) เลขที่ : 1/120 ซอยรามคำแหง 184 แขวงมีนบุรี เขตมีนบุรี กรุงเทพมหานคร 10510
A3: Tel : 0-2052-9544 Fax : 0-2052-9544 E-mail : sales@eitlaser.com
A14: (เอกสารฉบับนี้ถือเป็นความลับของบริษัท/ห้ามเผยแพร่)

Sheet ใบสรุป-69
A1: บริษัท ไอน์ชไตน์ อินดัสเตรียล เทคนิค คอร์ปอเรชั่น จำกัด (EIT)
A2: ใบสรุป-เงินเดือน
A3: ประจำปี 2569
A4: ชื่อ - นามสกุล | C4: Mr.Nakharin Angkapanompai
A5: Name - Surname | C5: นายนครินทร์ อังคะพนมไพร
A6: รหัสพนักงาน / Code Staff / ID | C6: 650321 | D6: 1209000128664
A7: แผนก / Department | C7: Technician
A8: ฝ่าย / Division | C8: Factory
A9: ตำแหน่ง / Position | C9: Technician
A10: วันที่เริ่มงาน | C10: 21/03/2565
A12: เดือน | B12: เงินเดือน | C12: ค่าล่วงเวลา | D12: ค่าเบี้ยขยัน | E12: ค่าคอมมิชชั่น | F12: อื่น ๆ | G12: อื่น ๆ | H12: Total | I12: อัตรา | J12: หัก ประกัน | K12: WHT-3% | L12: รับ-สุทธิ | M12: โอนเข้าบัญชี | O12: หมายเหตุ
B13: (บาท) | C13: Over time | E13: Commission | F13: Other | G13: (บาท) | H13: (บาท) | I13: SSO | J13: สังคม | K13: (บาท) | L13: (บาท) | M13: จำนวนเงิน (บาท) | N13: วันที่
A14: 2569
A15: มกราคม | B15: ='69-jan'!B16 -> 0 | C15: ='69-jan'!C16 -> 0 | D15: ='69-jan'!D16 -> 0 | E15: ='69-jan'!E16 -> 0 | F15: ='69-jan'!F16 -> 0 | G15: ='69-jan'!G16 -> 0 | H15: =SUM(B15:G15) -> 0 | I15: 5% | J15: =(17500)*I15 -> 875 | K15: =+-SUM(0)*3% -> 0 | L15: =H15-J15 -> -875 | M15: =L15 -> -875 | N15: 01/02/69
A16: กุมภาพันธ์ | B16: ='69-Feb'!B16 -> 0 | C16: ='69-Feb'!C16 -> 0 | D16: ='69-Feb'!D16 -> 0 | E16: ='69-Feb'!E16 -> 0 | F16: ='69-Feb'!F16 -> 0 | G16: ='69-Feb'!G16 -> 0 | H16: =SUM(B16:G16) -> 0 | I16: 5% | J16: =(17500)*I16 -> 875 | K16: =+-SUM(0)*3% -> 0 | L16: =H16-J16 -> -875 | M16: =L16 -> -875 | N16: 01/03/69
A17: มีนาคม | B17: ='69-Mar'!B16 -> 0 | C17: ='69-Mar'!C16 -> 0 | D17: ='69-Mar'!D16 -> 0 | E17: ='69-Mar'!E16 -> 0 | F17: ='69-Mar'!F16 -> 0 | G17: ='69-Mar'!G16 -> 0 | H17: =SUM(B17:G17) -> 0 | I17: 5% | J17: =(17500)*I17 -> 875 | K17: =+-SUM(0)*3% -> 0 | L17: =H17-J17 -> -875 | M17: =L17 -> -875 | N17: 01/04/69
A18: เมษายน | B18: ='69-Apr'!B16 -> 0 | C18: ='69-Apr'!C16 -> 0 | D18: ='69-Apr'!D16 -> 0 | E18: ='69-Apr'!E16 -> 0 | F18: ='69-Apr'!F16 -> 0 | G18: ='69-Apr'!G16 -> 0 | H18: =SUM(B18:G18) -> 0 | I18: 5% | J18: =(17500)*I18 -> 875 | K18: =+-SUM(0)*3% -> 0 | L18: =H18-J18 -> -875 | M18: =L18 -> -875 | N18: 01/05/69
A19: พฤษภาคม | B19: ='69-May'!B16 -> 0 | C19: ='69-May'!C16 -> 0 | D19: ='69-May'!D16 -> 0 | E19: ='69-May'!E16 -> 0 | F19: ='69-May'!F16 -> 0 | G19: ='69-May'!G16 -> 0 | H19: =SUM(B19:G19) -> 0 | I19: 5% | J19: =(17500)*I19 -> 875 | K19: =+-SUM(0)*3% -> 0 | L19: =H19-J19 -> -875 | M19: =L19 -> -875 | N19: 01/06/69
A20: มิถุนายน | B20: ='69-Jun'!B16 -> 0 | C20: ='69-Jun'!C16 -> 0 | D20: ='69-Jun'!D16 -> 0 | E20: ='69-Jun'!E16 -> 0 | F20: ='69-Jun'!F16 -> 0 | G20: ='69-Jun'!G16 -> 0 | H20: =SUM(B20:G20) -> 0 | I20: 5% | J20: =(17500)*I20 -> 875 | K20: =+-SUM(0)*3% -> 0 | L20: =H20-J20 -> -875 | M20: =L20 -> -875 | N20: 01/07/69
A21: กรกฎาคม | B21: ='69-Jul'!B16 -> 0 | C21: ='69-Jul'!C16 -> 0 | D21: ='69-Jul'!D16 -> 0 | E21: ='69-Jul'!E16 -> 0 | F21: ='69-Jul'!F16 -> 0 | G21: ='69-Jul'!G16 -> 0 | H21: =SUM(B21:G21) -> 0 | I21: 5% | J21: =(17500)*I21 -> 875 | K21: =+-SUM(0)*3% -> 0 | L21: =H21-J21 -> -875 | M21: =L21 -> -875 | N21: 01/08/69
A22: สิงหาคม | B22: ='69-Aug'!B16 -> 0 | C22: ='69-Aug'!C16 -> 0 | D22: ='69-Aug'!D16 -> 0 | E22: ='69-Aug'!E16 -> 0 | F22: ='69-Aug'!F16 -> 0 | G22: ='69-Aug'!G16 -> 0 | H22: =SUM(B22:G22) -> 0 | I22: 5% | J22: =(17500)*I22 -> 875 | K22: =+-SUM(0)*3% -> 0 | L22: =H22-J22 -> -875 | M22: =L22 -> -875 | N22: 01/09/69
A23: กันยายน | B23: ='69-Sep'!B16 -> 0 | C23: ='69-Sep'!C16 -> 0 | D23: ='69-Sep'!D16 -> 0 | E23: ='69-Sep'!E16 -> 0 | F23: ='69-Sep'!F16 -> 0 | G23: ='69-Sep'!G16 -> 0 | H23: =SUM(B23:G23) -> 0 | I23: 5% | J23: =(17500)*I23 -> 875 | K23: =+-SUM(0)*3% -> 0 | L23: =H23-J23 -> -875 | M23: =L23 -> -875 | N23: 01/10/69
A24: ตุลาคม | B24: ='69-Oct'!B16 -> 0 | C24: ='69-Oct'!C16 -> 0 | D24: ='69-Oct'!D16 -> 0 | E24: ='69-Oct'!E16 -> 0 | F24: ='69-Oct'!F16 -> 0 | G24: ='69-Oct'!G16 -> 0 | H24: =SUM(B24:G24) -> 0 | I24: 5% | J24: =(17500)*I24 -> 875 | K24: =+-SUM(0)*3% -> 0 | L24: =H24-J24 -> -875 | M24: =L24 -> -875 | N24: 01/11/69
A25: พฤศจิกายน | B25: ='69-Nov'!B16 -> 0 | C25: ='69-Nov'!C16 -> 0 | D25: ='69-Nov'!D16 -> 0 | E25: ='69-Nov'!E16 -> 0 | F25: ='69-Nov'!F16 -> 0 | G25: ='69-Nov'!G16 -> 0 | H25: =SUM(B25:G25) -> 0 | I25: 5% | J25: =(17500)*I25 -> 875 | K25: =+-SUM(0)*3% -> 0 | L25: =H25-J25 -> -875 | M25: =L25 -> -875 | N25: 01/12/69
A26: ธันวาคม | B26: ='69-Dec'!B16 -> 0 | C26: ='69-Dec'!C16 -> 0 | D26: ='69-Dec'!D16 -> 0 | E26: ='69-Dec'!E16 -> 0 | F26: ='69-Dec'!F16 -> 0 | G26: ='69-Dec'!G16 -> 0 | H26: =SUM(B26:G26) -> 0 | I26: 5% | J26: =(17500)*I26 -> 875 | K26: =+-SUM(0)*3% -> 0 | L26: =H26-J26 -> -875 | M26: =L26 -> -875 | N26: 01/01/70
A28: รวม | B28: =SUM(B15:B27) -> 0 | C28: =SUM(C15:C27) -> 0 | D28: =SUM(D15:D27) -> 0 | E28: =SUM(E15:E27) -> 0 | F28: =SUM(F15:F27) -> 0 | G28: =SUM(G15:G27) -> 0 | H28: =SUM(H15:H27) -> 0 | J28: =SUM(J15:J27) -> 10500 | K28: =SUM(K15:K27) -> 0 | L28: =SUM(L15:L27) -> -10500 | M28: =SUM(M15:M27) -> -10500
